{
	"Version": 3,
	"FileReferences": {
		"Moc": "CHA_Farkas_NPC_01.moc3",
		"Textures": [
			"CHA_Farkas_NPC_01.2048/texture_00.png"
		],
		"DisplayInfo": "CHA_Farkas_NPC_01.cdi3.json",
		"Expressions": [
			{
				"Name": "Idle",
				"File": "expressions/EMO_Farkas_Idle_01.exp3.json"
			},
			{
				"Name": "Panic",
				"File": "expressions/EMO_Farkas_Panic_01.exp3.json"
			},
			{
				"Name": "Smile",
				"File": "expressions/EMO_Farkas_Smile_01.exp3.json"
			}
		]
	},
	"Groups": [
		{
			"Target": "Parameter",
			"Name": "LipSync",
			"Ids": [
				"ParamMouthOpenY"
			]
		},
		{
			"Target": "Parameter",
			"Name": "EyeBlink",
			"Ids": [
				"ParamEyeLOpen",
				"ParamEyeROpen"
			]
		}
	],
	"HitAreas": []
}