{
	"Version": 3,
	"FileReferences": {
		"Moc": "CHA_Mosinnagant_SSR_01.moc3",
		"Textures": [
			"CHA_Mosinnagant_SSR_01.2048/texture_00.png"
		],
		"DisplayInfo": "CHA_Mosinnagant_SSR_01.cdi3.json",
		"Expressions": [
			{
				"Name": "Angry",
				"File": "exopressions/EMO_Mosinnagant_Angry_01.exp3.json"
			},
			{
				"Name": "Drunk",
				"File": "exopressions/EMO_Mosinnagant_Drunk_01.exp3.json"
			},
			{
				"Name": "Idle",
				"File": "exopressions/EMO_Mosinnagant_Idle_01.exp3.json"
			},
			{
				"Name": "Moved",
				"File": "exopressions/EMO_Mosinnagant_Moved_01.exp3.json"
			},
			{
				"Name": "Nervous",
				"File": "exopressions/EMO_Mosinnagant_Nervous_01.exp3.json"
			},
			{
				"Name": "Regretting",
				"File": "exopressions/EMO_Mosinnagant_Regretting_01.exp3.json"
			},
			{
				"Name": "Sad",
				"File": "exopressions/EMO_Mosinnagant_Sad_01.exp3.json"
			},
			{
				"Name": "Serious",
				"File": "exopressions/EMO_Mosinnagant_Serious_01.exp3.json"
			},
			{
				"Name": "Smile",
				"File": "exopressions/EMO_Mosinnagant_Smile_01.exp3.json"
			},
			{
				"Name": "Surprised",
				"File": "exopressions/EMO_Mosinnagant_Surprised_01.exp3.json"
			}
		],
		"Motions": {
			"": [
				{
					"File": "motions/Mouthopen_10s.motion3.json",
					"FadeInTime": 0,
					"FadeOutTime": 0
				},
				{
					"File": "motions/Mouthopen_2s.motion3.json"
				},
				{
					"File": "motions/Mouthopen_5s.motion3.json"
				}
			]
		}
	},
	"Groups": [
		{
			"Target": "Parameter",
			"Name": "EyeBlink",
			"Ids": [
				"ParamEyeROpen",
				"ParamEyeLOpen"
			]
		},
		{
			"Target": "Parameter",
			"Name": "LipSync",
			"Ids": [
				"ParamMouthOpenY"
			]
		}
	],
	"HitAreas": []
}